dynamo/common/__init__.py
dynamo/common/_version.py
dynamo/common/config_dump/__init__.py
dynamo/common/config_dump/config_dumper.py
dynamo/common/config_dump/environment.py
dynamo/common/config_dump/system_info.py
dynamo/common/utils/__init__.py
dynamo/common/utils/paths.py
dynamo/common/utils/prometheus.py
dynamo/frontend/README.md
dynamo/frontend/__init__.py
dynamo/frontend/__main__.py
dynamo/frontend/_version.py
dynamo/frontend/main.py
dynamo/mocker/README.md
dynamo/mocker/__init__.py
dynamo/mocker/__main__.py
dynamo/mocker/_version.py
dynamo/mocker/args.py
dynamo/mocker/main.py
dynamo/planner/README.md
dynamo/planner/__init__.py
dynamo/planner/_version.py
dynamo/planner/defaults.py
dynamo/planner/kube.py
dynamo/planner/kubernetes_connector.py
dynamo/planner/planner_connector.py
dynamo/planner/planner_sla.py
dynamo/planner/virtual_connector.py
dynamo/planner/utils/__init__.py
dynamo/planner/utils/dryrun_plot_utils.py
dynamo/planner/utils/exceptions.py
dynamo/planner/utils/load_predictor.py
dynamo/planner/utils/perf_interpolation.py
dynamo/planner/utils/planner_argparse.py
dynamo/planner/utils/planner_core.py
dynamo/planner/utils/pre_swept_results_utils.py
dynamo/planner/utils/prometheus.py
dynamo/planner/utils/trace_data_extractor.py
dynamo/planner/utils/pre_swept_results/h100_sxm/vllm/nvidia/Llama-3.3-70B-Instruct-FP8/decode.npz
dynamo/planner/utils/pre_swept_results/h100_sxm/vllm/nvidia/Llama-3.3-70B-Instruct-FP8/prefill.npz
dynamo/planner/utils/pre_swept_results/h200_sxm/vllm/nvidia/Llama-3.1-8B-Instruct-FP8/decode.npz
dynamo/planner/utils/pre_swept_results/h200_sxm/vllm/nvidia/Llama-3.1-8B-Instruct-FP8/prefill.npz
dynamo/router/README.md
dynamo/router/__init__.py
dynamo/router/__main__.py
dynamo/router/_version.py
dynamo/sglang/__init__.py
dynamo/sglang/__main__.py
dynamo/sglang/_version.py
dynamo/sglang/args.py
dynamo/sglang/health_check.py
dynamo/sglang/main.py
dynamo/sglang/protocol.py
dynamo/sglang/publisher.py
dynamo/sglang/register.py
ai_dynamo-0.7.1.dist-info/METADATA
ai_dynamo-0.7.1.dist-info/WHEEL
ai_dynamo-0.7.1.dist-info/licenses/LICENSE
ai_dynamo-0.7.1.dist-info/RECORD
