Metadata-Version: 2.4
Name: ai-dynamo
Version: 0.7.1
Summary: Distributed Inference Framework
Project-URL: Repository, https://github.com/ai-dynamo/dynamo.git
Author-email: "NVIDIA Inc." <sw-dl-dynamo@nvidia.com>
License: Apache-2.0
License-File: LICENSE
Keywords: distributed,dynamo,genai,inference,llm,nvidia
Classifier: Development Status :: 4 - Beta
Classifier: Intended Audience :: Developers
Classifier: Intended Audience :: Information Technology
Classifier: Intended Audience :: Science/Research
Classifier: License :: OSI Approved :: Apache Software License
Classifier: Operating System :: POSIX :: Linux
Classifier: Programming Language :: Python :: 3
Classifier: Programming Language :: Python :: 3.10
Classifier: Programming Language :: Python :: 3.11
Classifier: Programming Language :: Python :: 3.12
Classifier: Topic :: Scientific/Engineering
Classifier: Topic :: Scientific/Engineering :: Artificial Intelligence
Requires-Python: >=3.10
Requires-Dist: ai-dynamo-runtime==0.7.1
Requires-Dist: click<8.2.0
Requires-Dist: distro
Requires-Dist: fastapi>=0.115.0
Requires-Dist: filelock
Requires-Dist: kubernetes<33.0.0,>=32.0.1
Requires-Dist: prometheus-client<1.0,>=0.23.1
Requires-Dist: pytest>=8.3.4
Requires-Dist: setuptools
Requires-Dist: transformers<=4.57.1,>=4.56.0
Requires-Dist: typer
Requires-Dist: types-psutil>=7.0.0.20250218
Provides-Extra: sglang
Requires-Dist: nixl[cu12]<=0.7.1; extra == 'sglang'
Requires-Dist: sglang==0.5.4.post3; extra == 'sglang'
Requires-Dist: uvloop; extra == 'sglang'
Provides-Extra: trtllm
Requires-Dist: tensorrt-llm==1.2.0rc3; extra == 'trtllm'
Requires-Dist: uvloop; extra == 'trtllm'
Provides-Extra: vllm
Requires-Dist: nixl[cu12]<=0.7.1; extra == 'vllm'
Requires-Dist: uvloop; extra == 'vllm'
Requires-Dist: vllm[flashinfer]==0.11.0; extra == 'vllm'
